README.md
setup.py
saffron/__init__.py
saffron/accounts.py
saffron/cli.py
saffron/contracts.py
saffron/database.py
saffron/genesis.py
saffron/settings.py
saffron/utils.py
saffron_cli.egg-info/PKG-INFO
saffron_cli.egg-info/SOURCES.txt
saffron_cli.egg-info/dependency_links.txt
saffron_cli.egg-info/entry_points.txt
saffron_cli.egg-info/not-zip-safe
saffron_cli.egg-info/requires.txt
saffron_cli.egg-info/top_level.txt