Metadata-Version: 1.1
Name: saffron-cli
Version: 0.1.11
Summary: blockchain artifact development tools
Home-page: https://github.com/Lamden/saffron
Author: Lamden
Author-email: james@lamden.io
License: UNKNOWN
Download-URL: https://github.com/Lamden/saffron/archive/0.1.tar.gz
Keywords: testing,logging,cryptocurrency,smartcontracts,ethereum,dashboards
Platform: UNKNOWN
Classifier: Development Status :: 2 - Pre-Alpha
Classifier: Environment :: Console
Classifier: Environment :: Web Environment
Classifier: Environment :: No Input/Output (Daemon)
Classifier: Environment :: OpenStack
Classifier: Intended Audience :: Education
Classifier: Intended Audience :: Developers
Classifier: Intended Audience :: System Administrators
Classifier: License :: OSI Approved :: GNU General Public License v3 or later (GPLv3+)
Classifier: Operating System :: MacOS :: MacOS X
Classifier: Operating System :: Microsoft :: Windows
Classifier: Operating System :: POSIX
Classifier: Programming Language :: Python :: 3 :: Only
Classifier: Topic :: Software Development :: Version Control :: Git
Classifier: Topic :: Software Development :: Libraries
Classifier: Topic :: Education :: Computer Aided Instruction (CAI)
Classifier: Topic :: Office/Business :: Groupware
